AIEmailAutomationUtilityMacOs/EmailReplyAssistant.py
AIEmailAutomationUtilityMacOs/Email_Classification.py
AIEmailAutomationUtilityMacOs/Email_DocumentUploader.py
AIEmailAutomationUtilityMacOs/Email_Draft.py
AIEmailAutomationUtilityMacOs/Email_Read.py
AIEmailAutomationUtilityMacOs/Email_Upload_Document.py
AIEmailAutomationUtilityMacOs/Save_Draft.py
AIEmailAutomationUtilityMacOs/Save_Transaction.py
AIEmailAutomationUtilityMacOs/__init__.py
AIEmailAutomationUtilityMacOs-0.0.3.dist-info/LICENCE.txt
AIEmailAutomationUtilityMacOs-0.0.3.dist-info/METADATA
AIEmailAutomationUtilityMacOs-0.0.3.dist-info/WHEEL
AIEmailAutomationUtilityMacOs-0.0.3.dist-info/top_level.txt
AIEmailAutomationUtilityMacOs-0.0.3.dist-info/RECORD
