Metadata-Version: 2.1
Name: AIEmailAutomationUtilityMacOs
Version: 0.0.3
Summary: Checking AI-Email-Automation project in MacOS
Author: Proteus Technology PVT. LTD.
Author-email: <apps@baseinformation.com>
Keywords: python,first package
Classifier: Development Status :: 3 - Alpha
Classifier: Intended Audience :: Education
Classifier: Programming Language :: Python :: 2
Classifier: Programming Language :: Python :: 3
Classifier: Operating System :: MacOS :: MacOS X
Classifier: Operating System :: Microsoft :: Windows
License-File: LICENCE.txt
